pytcs_tecnoalarm/__init__.py
pytcs_tecnoalarm/api_models.py
pytcs_tecnoalarm/exceptions.py
pytcs_tecnoalarm/objects.py
pytcs_tecnoalarm/tcsession.py
pytcs_tecnoalarm-0.4.dist-info/METADATA
pytcs_tecnoalarm-0.4.dist-info/WHEEL
pytcs_tecnoalarm-0.4.dist-info/licenses/LICENSE
pytcs_tecnoalarm-0.4.dist-info/RECORD
