Metadata-Version: 2.4
Name: pytcs_tecnoalarm
Version: 0.4
Summary: LIbrary to interact with Tecnoalarm TCS app backend
Project-URL: Homepage, https://github.com/icovada/pytcs
Project-URL: Issues, https://github.com/icovada/pytcs/issues
Author-email: Federico Tabbò <federico@tabbo.it>
License-Expression: GPL-3.0
License-File: LICENSE
Classifier: Programming Language :: Python :: 3
Requires-Python: >=3.8
Requires-Dist: pydantic
Requires-Dist: requests
Requires-Dist: retry
